realtimeawssecretsmngr/__init__.py
realtimeawssecretsmngr/index.py
realtime_aws_secretsmngr-0.0.6.dist-info/LICENSE
realtime_aws_secretsmngr-0.0.6.dist-info/METADATA
realtime_aws_secretsmngr-0.0.6.dist-info/WHEEL
realtime_aws_secretsmngr-0.0.6.dist-info/top_level.txt
realtime_aws_secretsmngr-0.0.6.dist-info/RECORD
