Metadata-Version: 2.1
Name: realtime-aws-secretsmngr
Version: 0.0.6
Summary: Interface to provide callback or push events when secret is updated in aws
Home-page: https://github.com/vasudevan-palani/realtime-aws-secretsmngr
Author: Vasudevan Palani
Author-email: vasudevan.palani@gmail.com
License: TBD
Platform: UNKNOWN
Requires-Dist: appsync-client (>=0.0.10)
Requires-Dist: paho-mqtt (>=1.4.0)
